leecarter/__init__.py
leecarter/leecarter.py
leecarter-1.0.2.dist-info/LICENSE
leecarter-1.0.2.dist-info/METADATA
leecarter-1.0.2.dist-info/WHEEL
leecarter-1.0.2.dist-info/top_level.txt
leecarter-1.0.2.dist-info/RECORD
