Metadata-Version: 2.1
Name: leecarter
Version: 1.0.2
Summary: leecarter
Home-page: https://github.com/andy971022/leecarter
Author: Andy Chen
Author-email: andy97_861022_chen@hotmail.com
License: UNKNOWN
Platform: UNKNOWN
Classifier: Programming Language :: Python :: 3
Classifier: License :: OSI Approved :: MIT License
Classifier: Operating System :: OS Independent
Requires-Python: >=3.6
Requires-Dist: numpy (>=1.18.0)
